{
  "schemaVersion": 1,
  "productId": "dadurkevicius-dml6-vs-jcl-comparison",
  "profileId": "dml6-jcl-coverage-by-frequency-band",
  "bandId": "five-to-nine",
  "coverageCode": 0,
  "recordEncoding": "array",
  "fields": [
    {
      "id": "word",
      "label": "Word form",
      "type": "string"
    },
    {
      "id": "jclTokenCount",
      "label": "JCL token count",
      "type": "raw-token-count",
      "unit": "tokens"
    }
  ],
  "ordering": {
    "field": "jclTokenCount",
    "direction": "descending",
    "tieBreak": "word-ascending"
  },
  "records": [
    [
      "aachener",
      9
    ],
    [
      "aae",
      9
    ],
    [
      "aaib",
      9
    ],
    [
      "aaltio",
      9
    ],
    [
      "aandrius",
      9
    ],
    [
      "aaradhya",
      9
    ],
    [
      "aaronsas",
      9
    ],
    [
      "aavikas",
      9
    ],
    [
      "aaį",
      9
    ],
    [
      "abadą",
      9
    ],
    [
      "abajevičius",
      9
    ],
    [
      "abakienė",
      9
    ],
    [
      "abaką",
      9
    ],
    [
      "abaldujai",
      9
    ],
    [
      "abalis",
      9
    ],
    [
      "abarauskų",
      9
    ],
    [
      "abaravi",
      9
    ],
    [
      "abarenovas",
      9
    ],
    [
      "abarovic",
      9
    ],
    [
      "abattoir",
      9
    ],
    [
      "abatus",
      9
    ],
    [
      "abayatas",
      9
    ],
    [
      "abazoriuvienės",
      9
    ],
    [
      "abbasali",
      9
    ],
    [
      "abbiamo",
      9
    ],
    [
      "abboudas",
      9
    ],
    [
      "abdelali",
      9
    ],
    [
      "abdelattifo",
      9
    ],
    [
      "abdelatty",
      9
    ],
    [
      "abdelkaderą",
      9
    ],
    [
      "abdelmoumene",
      9
    ],
    [
      "abdelrahimas",
      9
    ],
    [
      "abderos",
      9
    ],
    [
      "abdiazizas",
      9
    ],
    [
      "abdikadiras",
      9
    ],
    [
      "abdol",
      9
    ],
    [
      "abdos",
      9
    ],
    [
      "abdrachmanovo",
      9
    ],
    [
      "abdulahas",
      9
    ],
    [
      "abdulovu",
      9
    ],
    [
      "abdulovui",
      9
    ],
    [
      "abecelę",
      9
    ],
    [
      "abeciūnui",
      9
    ],
    [
      "abeciūną",
      9
    ],
    [
      "abegneilas",
      9
    ],
    [
      "abejojancius",
      9
    ],
    [
      "abejojų",
      9
    ],
    [
      "abejonų",
      9
    ],
    [
      "abelkiu",
      9
    ],
    [
      "abera",
      9
    ]
  ]
}
