{"schemaVersion":1,"productId":"utka-ccll-wordforms","viewId":"periodicals-by-frequency","chunk":290,"records":[["pasieninė",1],["pasieniuos",1],["pasienkinimo",1],["pasientui",1],["pasienyjr",1],["pasienyję",1],["pasienėse",1],["pasiesarčių",1],["pasietas",1],["pasieti",1],["pasietą",1],["pasieškodavo",1],["pasieškok",1],["pasieškokime",1],["pasifaje",1],["pasifarfaranyt",1],["pasifdarė",1],["pasifechtavimui",1],["pasifik",1],["pasifikator",1],["pasifiko",1],["pasifiku",1],["pasiflorinių",1],["pasiflorą",1],["pasifotografuoti",1],["pasigabens",1],["pasigadinusi",1],["pasigailejimo",1],["pasigailim",1],["pasigailime",1],["pasigailinti",1],["pasigailėdavę",1],["pasigailėjimų",1],["pasigailėjot",1],["pasigailėjote",1],["pasigailėjus",1],["pasigailėjusios",1],["pasigailėjusį",1],["pasigailėki",1],["pasigailėkime",1],["pasigailėsiu",1],["pasigailėsią",1],["pasigailėsiąs",1],["pasigailėtas",1],["pasigailėtinais",1],["pasigailėtinam",1],["pasigailėtiniems",1],["pasigailėtinos",1],["pasigailėtume",1],["pasigailęs",1],["pasigainiojau",1],["pasigainioti",1],["pasigalandau",1],["pasigalandu",1],["pasigalandęs",1],["pasigalvoti",1],["pasigalynėjo",1],["pasigalynėjęs",1],["pasigalynėsi",1],["pasigalynėsim",1],["pasigalėjo",1],["pasigalėsit",1],["pasigalėtiną",1],["pasigamibnti",1],["pasigaminai",1],["pasigaminam",1],["pasigaminamas",1],["pasigaminamos",1],["pasigaminančiomis",1],["pasigamindami",1],["pasigamindavome",1],["pasigamini",1],["pasigaminimui",1],["pasigaminkit",1],["pasigaminote",1],["pasigaminsi",1],["pasigaminsiu",1],["pasigaminsiąs",1],["pasigamint",1],["pasigamintoji",1],["pasigaminusiai",1],["pasigaminusiuose",1],["pasigaminusius",1],["pasigamti",1],["pasiganant",1],["pasigano",1],["pasiganys",1],["pasiganė",1],["pasigarbindavo",1],["pasigarbino",1],["pasigardina",1],["pasigardino",1],["pasigarsina",1],["pasigarsindamas",1],["pasigarsinimo",1],["pasigarsinimu",1],["pasigarsinta",1],["pasigarsinu",1],["pasigarsinę",1],["pasigaudami",1],["pasigaudavome",1],["pasigaudydavo",1],["pasigaudys",1],["pasigauk",1],["pasigaukite",1],["pasigaunamais",1],["pasigaunami",1],["pasigauni",1],["pasigauną",1],["pasigausi",1],["pasigausime",1],["pasigausite",1],["pasigaut",1],["pasigauta",1],["pasigautas",1],["pasigautos",1],["pasigautu",1],["pasigavusiam",1],["pasigavusiems",1],["pasigavusioje",1],["pasigedusiai",1],["pasigedusiems",1],["pasigedusios",1],["pasigedusių",1],["pasigelbėdama",1],["pasigelbėdami",1],["pasigen",1],["pasigendamas",1],["pasigendamus",1],["pasigendančioms",1],["pasigendančios",1],["pasigendančius",1],["pasigerdamas",1],["pasigeri",1],["pasigeriame",1],["pasigeriančios",1],["pasigerinant",1],["pasigerinau",1],["pasigerino",1],["pasigerins",1],["pasigerintų",1],["pasigerinusius",1],["pasigerkime",1],["pasigersime",1],["pasigersit",1],["pasigersiu",1],["pasigertum",1],["pasigertumėt",1],["pasigertų",1],["pasigerėjimu",1],["pasigerėjimui",1],["pasigerėtinu",1],["pasigesdavai",1],["pasigesianti",1],["pasigesią",1],["pasigestu",1],["pasigestum",1],["pasigilina",1],["pasigiliname",1],["pasigilinome",1],["pasigilinsiu",1],["pasigilint",1],["pasigilintumėte",1],["pasigilintų",1],["pasigilinusi",1],["pasigilinusiam",1],["pasigilinusio",1],["pasigimdyk",1],["pasigimdys",1],["pasigimdyčiau",1],["pasigimdėme",1],["pasigiminiuoti",1],["pasigimnastikavus",1],["pasigimnastikuotų",1],["pasiginti",1],["pasiginčijama",1],["pasiginčijau",1],["pasiginčiji",1],["pasiginčijimai",1],["pasiginčijimo",1],["pasiginčijusi",1],["pasiginčyjam",1],["pasiginčys",1],["pasiginčysim",1],["pasiginčysime",1],["pasiginčysiu",1],["pasiginčyt",1],["pasiginčytų",1],["pasiginčyčiau",1],["pasigirdamas",1],["pasigirdavau",1],["pasigirdi",1],["pasigirgo",1],["pasigiriame",1],["pasigirk",1],["pasigirkime",1],["pasigirsime",1],["pasigirsią",1],["pasigirstamomis",1],["pasigirstančia",1],["pasigirstančioms",1],["pasigirstančiu",1],["pasigirta",1],["pasiglamonėjama",1],["pasiglamonėjame",1],["pasiglaustymui",1],["pasiglaustymų",1],["pasiglaustyti",1],["pasiglaustytų",1],["pasiglausčiau",1],["pasiglostant",1],["pasiglostydamas",1],["pasiglostymų",1],["pasiglostys",1],["pasiglostyti",1],["pasiglėbesčiavimais",1],["pasiglėbesčiavę",1],["pasiglėbesčiuodavo",1],["pasiglėbesčiuoti",1],["pasignaibymais",1],["pasignaibymo",1],["pasignalinom",1],["pasignalizavote",1],["pasigodojimai",1],["pasigodojo",1],["pasigodėjimo",1],["pasigodėjo",1],["pasigrabalioti",1],["pasigraibsčiusi",1],["pasigraibydami",1],["pasigraibymai",1],["pasigraibymais",1],["pasigraibė",1],["pasigraibę",1],["pasigramdydavo",1],["pasigrasinusioje",1],["pasigraudenta",1],["pasigriebiame",1],["pasigriebiant",1],["pasigriebiu",1],["pasigriebta",1],["pasigriebtų",1],["pasigriebusi",1],["pasigrimavę",1],["pasigrobiančiai",1],["pasigrobimas",1],["pasigrobs",1],["pasigrobstymo",1],["pasigrobt",1],["pasigrobta",1],["pasigrobtais",1],["pasigrobtomis",1],["pasigrobtos",1],["pasigrobusia",1],["pasigrobusios",1],["pasigrobusią",1],["pasigrobusį",1],["pasigroju",1],["pasigrokit",1],["pasigroti",1],["pasigrybaut",1],["pasigrįsti",1],["pasigrūdino",1],["pasiguldau",1],["pasiguldei",1],["pasiguldomas",1],["pasiguldyk",1],["pasiguldysite",1],["pasiguldytumėt",1],["pasiguldėm",1],["pasiguldėme",1],["pasiguodei",1],["pasiguodimais",1],["pasiguodimu",1],["pasiguodimui",1],["pasiguodimus",1],["pasiguodėme",1],["pasiguodėt",1],["pasiguosdavome",1],["pasiguosdavęs",1],["pasiguosiu",1],["pasiguoski",1],["pasiguoskite",1],["pasiguostum",1],["pasiguostume",1],["pasigvelbti",1],["pasigviešusi",1],["pasigviešusieji",1],["pasigydei",1],["pasigydykime",1],["pasigydykite",1],["pasigydymui",1],["pasigydysianti",1],["pasigydysite",1],["pasigyrimu",1],["pasigyrimą",1],["pasigyrėt",1],["pasigąsdinimų",1],["pasigėdijau",1],["pasigėdijo",1],["pasigėdys",1],["pasigėrime",1],["pasigėrimų",1],["pasigėrusiems",1],["pasigėrėdami",1],["pasigėrėjus",1],["pasigėrėjusi",1],["pasigėrėme",1],["pasigėrės",1],["pasigėrėsiu",1],["pasigėrėt",1],["pasigėrėta",1],["pasigėrėte",1],["pasigėrėtini",1],["pasigėrėtino",1],["pasigėrėtum",1],["pasigėrėčiau",1],["pasigęs",1],["pasigęsta",1],["pasiieškodamas",1],["pasiieškodavo",1],["pasiieškodavęs",1],["pasiieškojimo",1],["pasiieškojusi",1],["pasiieškoję",1],["pasiieškokit",1],["pasiieškot",1],["pasiieškotum",1],["pasiieškotumėt",1],["pasiieškočiau",1],["pasiilgdavome",1],["pasiilgdavusi",1],["pasiilgimai",1],["pasiilgimus",1],["pasiilgimų",1],["pasiilgindavome",1],["pasiilgintų",1],["pasiilgova",1],["pasiilgsim",1],["pasiilgsit",1],["pasiilgsiąs",1],["pasiilgstamai",1],["pasiilgstantiems",1],["pasiilgstančią",1],["pasiilgstat",1],["pasiilgsto",1],["pasiilgto",1],["pasiilgtoje",1],["pasiilgtu",1],["pasiilgtume",1],["pasiilgtąja",1],["pasiilgtų",1],["pasiilgusia",1],["pasiilgusiai",1],["pasiilgusiajam",1],["pasiilgusiomis",1],["pasiilgusiu",1],["pasiilgusiuose",1],["pasiilgusį",1],["pasiilgėliams",1],["pasiilsint",1],["pasiilsinčių",1],["pasiilsite",1],["pasiilsiu",1],["pasiilsėdami",1],["pasiilsėk",1],["pasiilsėtų",1],["pasiimamos",1],["pasiimantys",1],["pasiimančiam",1],["pasiimdavote",1],["pasiimdavusi",1],["pasiimdavusios",1],["pasiiminėjant",1],["pasiiminėjo",1],["pasiiminėt",1],["pasiimke",1],["pasiimkim",1],["pasiimtajai",1],["pasiimtasis",1],["pasiimto",1],["pasiimtoji",1],["pasiimtu",1],["pasiimtumėm",1],["pasiimtuoju",1],["pasiirinktas",1],["pasiirstydavom",1],["pasiirstymas",1],["pasiirstymą",1],["pasiirstytų",1],["pasiirstė",1],["pasiirti",1],["pasijauninimo",1],["pasijauninusi",1],["pasijausdavome",1],["pasijausime",1],["pasijauskite",1],["pasijaustumėme",1],["pasijautau",1],["pasijautimas",1],["pasijautusi",1],["pasijautėm",1],["pasijautėte",1],["pasijautę",1],["pasijaučiama",1],["pasijaučiantis",1],["pasijeme",1],["pasijodinėdavusiu",1],["pasijodinėjimu",1],["pasijodinėjimui",1],["pasijomis",1],["pasijoniai",1],["pasijonio",1],["pasijonius",1],["pasijont",1],["pasijot",1],["pasijotus",1],["pasijotų",1],["pasijudin",1],["pasijudinimai",1],["pasijudinęs",1],["pasijungdavo",1],["pasijungimo",1],["pasijungus",1],["pasijungė",1],["pasijungę",1],["pasijungęs",1],["pasijuntanti",1],["pasijuntantį",1],["pasijuokdavau",1],["pasijuokim",1],["pasijuokimu",1],["pasijuokimų",1],["pasijuoktume",1],["pasijuokus",1],["pasijuokėte",1],["pasijuoti",1],["pasijusdami",1],["pasijusdavom",1],["pasijusit",1],["pasijuskite",1],["pasijusta",1],["pasijutusiais",1],["pasijutusieji",1],["pasijutusiems",1],["pasijėmį",1],["pasikabiname",1],["pasikabindamos",1],["pasikabindavo",1],["pasikabinimas",1],["pasikabinkit",1],["pasikabinsime",1],["pasikabinsiu",1],["pasikabinusio",1],["pasikabinusių",1],["pasikaitinimas",1],["pasikaitino",1],["pasikaitinome",1],["pasikaitinsim",1],["pasikaitinu",1],["pasikaišius",1],["pasikaišiusią",1],["pasikaišo",1],["pasikaišydavo",1],["pasikaišė",1],["pasikaišę",1],["pasikal",1],["pasikalbant",1],["pasikalbanti",1],["pasikalbantis",1],["pasikalbantys",1],["pasikalbinti",1],["pasikalbinę",1],["pasikalbinęs",1],["pasikalbąs",1],["pasikalbėdama",1],["pasikalbėdamas",1],["pasikalbėdavęs",1],["pasikalbėjote",1],["pasikalbėjova",1],["pasikalbėsi",1],["pasikalbėsianti",1],["pasikalbėsit",1],["pasikalbėto",1],["pasikalbėtojo",1],["pasikalbėtum",1],["pasikalbėtumėm",1],["pasikalti",1],["pasikaltoja",1],["pasikamavo",1],["pasikamavusi",1],["pasikamavusiam",1],["pasikamavęs",1],["pasikandusios",1],["pasikankinkite",1],["pasikankins",1],["pasikankinsime",1],["pasikankintų",1],["pasikankinę",1],["pasikapodamas",1],["pasikapojimas",1],["pasikapstot",1],["pasikapstyk",1],["pasikapstymas",1],["pasikapstys",1],["pasikapstysi",1],["pasikapstytum",1],["pasikapsčiau",1],["pasikardama",1],["pasikardami",1],["pasikariame",1],["pasikariančius",1],["pasikarsi",1],["pasikarsią",1],["pasikartodami",1],["pasikartodamos",1],["pasikartodavau",1],["pasikartodavusią",1],["pasikartojami",1],["pasikartojamumas",1],["pasikartojančiame",1],["pasikartojančiom",1],["pasikartojančioms",1],["pasikartojau",1],["pasikartoji",1],["pasikartojimuose",1],["pasikartojusia",1],["pasikartojusiame",1],["pasikartojusio",1],["pasikartojusią",1],["pasikartojąs",1],["pasikartokime",1],["pasikartotinai",1],["pasikartotis",1],["pasikarčiuos",1],["pasikarščiavimai",1],["pasikarščiavimus",1],["pasikarščiavus",1],["pasikarščiuodavo",1],["pasikarščiuojate",1],["pasikarščiuoji",1],["pasikasant",1],["pasikasimai",1],["pasikasimas",1],["pasikasime",1],["pasikasimuose",1],["pasikasimų",1],["pasikasinėjimą",1],["pasikasinėjus",1],["pasikasiu",1],["pasikaskime",1],["pasikasusi",1],["pasikasydami",1],["pasikasykite",1],["pasikasymo",1],["pasikasys",1],["pasikasysiu",1],["pasikasytum",1],["pasikasytų",1],["pasikasyčiau",1],["pasikasėm",1],["pasikaustydamos",1],["pasikaustymas",1],["pasikaustyti",1],["pasikausčiau",1],["pasikausčius",1],["pasikausčiusiais",1],["pasikausčiusiems",1],["pasikausčiusios",1],["pasikausčiusių",1],["pasikavoja",1],["pasikavojęs",1],["pasikedenimus",1],["pasikei",1],["pasikeik",1],["pasikeikianti",1],["pasikeikiu",1],["pasikeiksnojimai",1],["pasikeiksnojimu",1],["pasikeiksnoti",1],["pasikeikti",1],["pasikeisdama",1],["pasikeisdavom",1],["pasikeisdavęs",1],["pasikeisiant",1],["pasikeisianti",1],["pasikeisiančia",1],["pasikeisiančio",1],["pasikeisiančių",1],["pasikeiskim",1],["pasikeistumėm",1],["pasikeistumėte",1],["pasikeistuoju",1],["pasikeistė",1],["pasikeisčiau",1],["pasikeitimasis",1],["pasikeitmo",1],["pasikeitusiems",1],["pasikeitusioj",1],["pasikeitusiųjų",1],["pasikeitėlis",1],["pasikeičiami",1],["pasikeičiamos",1],["pasikeičianti",1],["pasikeičiantys",1],["pasikeičiančiais",1],["pasikeičiančios",1],["pasikeičiąs",1],["pasikeiė",1],["pasikeldama",1],["pasikeldavau",1],["pasikeldavome",1],["pasikeliame",1],["pasikeliančia",1],["pasikeliančių",1],["pasikeliu",1],["pasikelkite",1],["pasikelsi",1],["pasikelsime",1],["pasikelt",1],["pasikepdavau",1],["pasikepinti",1],["pasikepinę",1],["pasikepu",1],["pasikepė",1],["pasikepšnojant",1],["pasikerpu",1],["pasikesinta",1],["pasiketimai",1],["pasiketimais",1],["pasiketimas",1],["pasiketimą",1],["pasiketinimai",1],["pasiketusį",1],["pasikečia",1],["pasikiaušiniauti",1],["pasikieminėdavo",1],["pasikikendamas",1],["pasikikendami",1],["pasikikensim",1],["pasikilnos",1],["pasikinkau",1],["pasikinkiusių",1],["pasikinkom",1],["pasikinkome",1],["pasikinkydavo",1],["pasikinkydavome",1],["pasikinkys",1],["pasikinkysime",1],["pasikinkyt",1],["pasikinkytum",1],["pasikinkėme",1],["pasikirpdavau",1],["pasikirpk",1],["pasikirpo",1],["pasikirpti",1],["pasikirpusi",1],["pasikirsta",1],["pasikirstymas",1],["pasikirsčiusiesiems",1],["pasikirtas",1],["pasikirtau",1],["pasikivirčyti",1],["pasikiši",1],["pasikiškiakopūsteliaudami",1],["pasikiškopūsteliaudamas",1],["pasikišt",1],["pasikišu",1],["pasikjeitimų",1],["pasiklaiuti",1],["pasiklauk",1],["pasiklausant",1],["pasiklausantieji",1],["pasiklausančių",1],["pasiklausdama",1],["pasiklausdamas",1],["pasiklausdami",1],["pasiklausinėjo",1],["pasiklausinėju",1],["pasiklausinėję",1],["pasiklausinėkite",1],["pasiklausinėsime",1],["pasiklausinėtų",1],["pasiklausom",1],["pasiklausomas",1],["pasiklaust",1],["pasiklaustum",1],["pasiklaustų",1],["pasiklausyc",1],["pasiklausydami",1],["pasiklausydamos",1],["pasiklausydavom",1],["pasiklausysim",1],["pasiklausysią",1],["pasiklausytie",1],["pasiklausyto",1],["pasiklausytoja",1],["pasiklausytumi",1],["pasiklausytumėte",1],["pasiklausėm",1],["pasiklauti",1],["pasiklautinieji",1],["pasikliaujamieji",1],["pasikliaujantieji",1],["pasikliaujantiems",1],["pasikliaujančiais",1],["pasikliaujančioje",1],["pasikliaujančiu",1],["pasikliaujančius",1],["pasikliaujančią",1],["pasikliauname",1],["pasikliaunantiems",1],["pasikliaunate",1],["pasikliauną",1],["pasikliausim",1],["pasikliausite",1],["pasikliausiu",1],["pasikliautinas",1],["pasikliautinuoju",1],["pasikliautum",1],["pasikliaučiau",1],["pasikliovusiai",1],["pasikliovusių",1],["pasiklodavom",1],["pasiklojant",1],["pasiklojom",1],["pasiklojus",1],["pasiklojusios",1],["pasiklokime",1],["pasiklokite",1],["pasiklonioja",1],["pasikloniokim",1],["pasiklosim",1],["pasiklosit",1],["pasikloto",1],["pasikločiau",1],["pasiklydimą",1],["pasiklydom",1],["pasiklydusioje",1],["pasiklydusiomis",1],["pasiklydusiu",1],["pasiklydusiųjų",1],["pasiklydėles",1],["pasiklydėliai",1],["pasiklydėlius",1],["pasiklydėlių",1],["pasiklydėlė",1],["pasiklysdavome",1],["pasiklyst",1],["pasiklystam",1],["pasiklystanti",1],["pasiklystantiems",1],["pasiklystančio",1],["pasiklystančią",1],["pasiklystum",1],["pasiknaisioja",1],["pasiknaisiojau",1],["pasiknaisiojimą",1],["pasiknaisiojo",1],["pasiknaisiojus",1],["pasiknaisę",1],["pasiknisau",1],["pasikniso",1],["pasiknisusia",1],["pasikolinti",1],["pasikoliojau",1],["pasikolioti",1],["pasikonsultavusios",1],["pasikonsultuodami",1],["pasikonsultuojame",1],["pasikonsultuoju",1],["pasikonsultuosime",1],["pasikonsultuosite",1],["pasikonsultuosiąs",1],["pasikonsultuota",1],["pasikore",1],["pasikoregavo",1],["pasikoregavusi",1],["pasikoregavusios",1],["pasikoreguoti",1],["pasikorei",1],["pasikoriau",1],["pasikorimas",1],["pasikorusiu",1],["pasikorusių",1],["pasikovskis",1],["pasikraipiusios",1],["pasikraipo",1],["pasikraipydamos",1],["pasikraipydavome",1],["pasikraipyti",1],["pasikrapštai",1],["pasikrapštinėja",1],["pasikrapštydamas",1],["pasikrapštykit",1],["pasikrapštymams",1],["pasikrapštymo",1],["pasikrapštys",1],["pasikrapštytų",1],["pasikrapštėm",1],["pasikrapštę",1],["pasikrapščiau",1],["pasikrapščius",1],["pasikratom",1],["pasikratymo",1],["pasikraunančiais",1],["pasikraus",1],["pasikrausiu",1],["pasikračiusios",1],["pasikreipusios",1],["pasikreipęs",1],["pasikrečia",1],["pasikrikštijant",1],["pasikrikštijau",1],["pasikrikštijusiam",1],["pasikrikštijusio",1],["pasikrikštijusios",1],["pasikrikštijusius",1],["pasikrikštijusiųjų",1],["pasikrikštykite",1],["pasikrikštysiu",1],["pasikrovus",1],["pasikrovusio",1],["pasikrovusios",1],["pasikrėtusius",1],["pasikuitė",1],["pasikuitę",1],["pasikuitęs",1],["pasikuičia",1],["pasikuklina",1],["pasikuklinai",1],["pasikuklindamas",1],["pasikuklinta",1],["pasikuklinus",1],["pasikuklinusių",1],["pasikukčiodamos",1],["pasikulti",1],["pasikumščiavimai",1],["pasikumščiavimas",1],["pasikumščiavimo",1],["pasikumščiavom",1],["pasikumščiuodavo",1],["pasikuprojusį",1],["pasikurdavo",1],["pasikuriu",1],["pasikurs",1],["pasikursi",1],["pasikursime",1],["pasikursiu",1],["pasikutenk",1],["pasikutensim",1],["pasikuštėjusios",1],["pasikuštėjęs",1],["pasikvatodama",1],["pasikvatoti",1],["pasikvepink",1],["pasikviedamas",1],["pasikvientė",1],["pasikviesdavai",1],["pasikviesite",1],["pasikviest",1],["pasikviestam",1],["pasikviesto",1],["pasikviestomis",1],["pasikviestumei",1],["pasikvietimas",1],["pasikvietimo",1],["pasikvietimu",1],["pasikvietusiems",1],["pasikvietusio",1],["pasikvietusius",1],["pasikviečiamos",1],["pasikviečiančių",1],["pasikvėpinai",1],["pasikvėpinau",1],["pasikvėpindavo",1],["pasikvėpinus",1],["pasikvėpinęs",1],["pasikósinimą",1],["pasikćuti",1],["pasikėlauti",1],["pasikėlimo",1],["pasikėlimui",1],["pasikėlusiam",1],["pasikėsiminą",1],["pasikėsimus",1],["pasikėsinau",1],["pasikėsindama",1],["pasikėsindamas",1],["pasikėsindami",1],["pasikėsinome",1],["pasikėsinsią",1],["pasikėsintojus",1],["pasikėsinusiais",1],["pasikėsinusieji",1],["pasikėsinusio",1],["pasikėsinusioje",1],["pasikėsinusiomis",1],["pasikėsinusios",1],["pasikėsinusiuoju",1],["pasikėsta",1],["pasikūkčiodamos",1],["pasikūprinti",1],["pasikūrena",1],["pasikūrenam",1],["pasikūrendavo",1],["pasikūreni",1],["pasikūrusi",1],["pasikūrė",1],["pasilabinama",1],["pasilabindavom",1],["pasilabini",1],["pasilabinimų",1],["pasilabins",1],["pasilabinsime",1],["pasilabint",1],["pasilabinu",1],["pasilabinusi",1],["pasilaidijo",1],["pasilaidojimai",1],["pasilaidojimo",1],["pasilaidojimą",1],["pasilaidok",1],["pasilaidokim",1],["pasilaidos",1],["pasilaidosi",1],["pasilaidosime",1],["pasilaidočiau",1],["pasilaidymai",1],["pasilaikau",1],["pasilaikiusi",1],["pasilaikusi",1],["pasilaikydama",1],["pasilaikydavę",1],["pasilaikykime",1],["pasilaikymo",1],["pasilaikymų",1],["pasilaikysim",1],["pasilaikęs",1],["pasilaistymai",1],["pasilaistyta",1],["pasilaisvinę",1],["pasilakstymui",1],["pasilakstymą",1],["pasilakstyt",1],["pasilakstę",1],["pasilankstyk",1],["pasilankstykite",1],["pasilankstymais",1],["pasilankyti",1],["pasilankė",1],["pasilankėme",1],["pasilauskas",1],["pasilausydami",1],["pasilavinęs",1],["pasile",1],["pasilegti",1],["pasileidime",1],["pasileiduio",1],["pasileidusia",1],["pasileidusiam",1],["pasileidusias",1],["pasileidusio",1],["pasileidusius",1],["pasileidusią",1],["pasileidusį",1],["pasileidėlei",1],["pasileidėliais",1],["pasileidėlio",1],["pasileidėliški",1],["pasileidėliškumo",1],["pasileisdamas",1],["pasileisdavau",1],["pasileisi",1],["pasileisim",1],["pasileisčiau",1],["pasilengvina",1],["pasilengvinai",1],["pasilengvindamas",1],["pasilengvindavo",1],["pasilengvino",1],["pasilengvintume",1],["pasilenkiame",1],["pasilenkimas",1],["pasilenkimo",1],["pasilenkimų",1],["pasilenksime",1],["pasilenkt",1],["pasilenktum",1],["pasilenktą",1],["pasilenktų",1],["pasilenkusiajam",1],["pasilenkusius",1],["pasilenkčiau",1],["pasilenkėm",1],["pasilepindavau",1],["pasilepindavo",1],["pasilepinsi",1],["pasilepinsime",1],["pasilepinusi",1],["pasilepinęs",1],["pasilgai",1],["pasilgstu",1],["pasilgtu",1],["pasili",1],["pasilie",1],["pasiliedavo",1],["pasiliejus",1],["pasilieję",1],["pasiliekam",1],["pasiliekantiesiems",1],["pasiliekančia",1],["pasiliekančiam",1],["pasiliekančioje",1],["pasiliekančiuose",1],["pasiliekančius",1],["pasiliekat",1],["pasilieknino",1],["pasilietuvinom",1],["pasilietų",1],["pasiligodavo",1],["pasiligojimą",1],["pasiligojusia",1],["pasiligojusiai",1],["pasiligojusioms",1],["pasiligojusiųjų",1],["pasilikam",1],["pasilikdavęs",1],["pasilikim",1],["pasilikimui",1],["pasilikinėjo",1],["pasiliksianti",1],["pasiliksiantį",1],["pasiliksiančiuosius",1],["pasiliktais",1],["pasiliktti",1],["pasiliktumėme",1],["pasiliktumėt",1],["pasiliktumėte",1],["pasilikusia",1],["pasilikusiame",1],["pasilikusiomis",1],["pasilindimui",1],["pasilindęs",1],["pasilingavimai",1],["pasilinguodama",1],["pasilinguodamas",1],["pasilinksm",1],["pasilinksmindavom",1],["pasilinksmindavome",1],["pasilinksmindavusios",1],["pasilinksminimuos",1],["pasilinksminsi",1],["pasilinksminsim",1],["pasilinksminsime",1],["pasilinksminsit",1],["pasilinksmintojus",1],["pasilinksmintum",1],["pasilinksminu",1],["pasilinksminusius",1],["pasilinksminusių",1],["pasiliovus",1],["pasilipi",1],["pasilipo",1],["pasilipt",1],["pasilipėjus",1],["pasilipę",1],["pasiliuobk",1],["pasiliuosavę",1],["pasiliuosiuoti",1],["pasiliuosuotum",1],["pasiliustruoti",1],["pasilklystame",1],["pasilonk",1],["pasilonkės",1],["pasilopysiu",1],["pasilopyti",1],["pasilpnintas",1],["pasilpome",1],["pasilpusi",1],["pasilpusiems",1],["pasilpę",1],["pasilpęs",1],["pasilsėjom",1],["pasilsėjusiomis",1],["pasilsėjęs",1],["pasilsėsi",1],["pasilsėsime",1],["pasilsėtum",1],["pasilsėtumėm",1],["pasilyginimas",1],["pasilygino",1],["pasilyginsime",1],["pasilyginę",1],["pasilypėdama",1],["pasilypėdavau",1],["pasilypėdavome",1],["pasilypėjančią",1],["pasilypėjau",1],["pasilypėjome",1],["pasilypėjusio",1],["pasilypėk",1],["pasilypėkime",1],["pasilėpdavau",1],["pasilėpus",1],["pasima",1],["pasimainymui",1],["pasimainyti",1],["pasimaistauti",1],["pasimaitindama",1],["pasimaitindamas",1],["pasimaitink",1],["pasimaitinus",1],["pasimaitinusi",1],["pasimaivant",1],["pasimaiviusi",1],["pasimaivom",1],["pasimaivęs",1],["pasimaišančius",1],["pasimaišei",1],["pasimaišiusi",1],["pasimaišiusios",1],["pasimaišiusius",1],["pasimaišiusią",1],["pasimaišymo",1],["pasimaišys",1],["pasimakaluosiu",1],["pasimalkaujama",1],["pasimaloninsim",1],["pasimalsim",1],["pasimalę",1],["pasimankštinate",1],["pasimankštinimui",1],["pasimankštinsi",1],["pasimankštinus",1],["pasimankštinusi",1],["pasimankštinusios",1],["pasimankštinčiau",1],["pasimatai",1],["pasimatanti",1],["pasimatančios",1],["pasimatavimo",1],["pasimatavimu",1],["pasimatavę",1],["pasimatote",1],["pasimatuodavau",1],["pasimatuok",1],["pasimatuokim",1],["pasimatuos",1],["pasimatuotųjų",1],["pasimatydamas",1],["pasimatydavome",1],["pasimatymiškiausią",1],["pasimatysi",1],["pasimatysiu",1],["pasimatysią",1],["pasimatysiąs",1],["pasimatytis",1],["pasimatytum",1],["pasimatytume",1],["pasimatytumei",1],["pasimaudo",1],["pasimaudom",1],["pasimaudydavom",1],["pasimaudymas",1],["pasimaudysi",1],["pasimaudėm",1],["pasimaudęs",1],["pasimaunančių",1],["pasimauni",1],["pasimbolizuos",1],["pasimegauti",1],["pasimeilinimai",1],["pasimeilino",1],["pasimeldimas",1],["pasimeldimu",1],["pasimeldusios",1],["pasimelsdavau",1],["pasimelsdavome",1],["pasimelski",1],["pasimelskim",1],["pasimelskit",1],["pasimelš",1],["pasimentę",1],["pasimerkdavau",1],["pasimerkime",1],["pasimerkti",1],["pasimerkėte",1],["pasimesdama",1],["pasimesdami",1],["pasimesdavau",1],["pasimesime",1],["pasimestum",1],["pasimestume",1],["pasimesčiau",1],["pasimetam",1],["pasimetantys",1],["pasimetančioms",1],["pasimetančių",1],["pasimetate",1],["pasimetelis",1],["pasimetes",1],["pasimetimus",1],["pasimetsius",1],["pasimetusiomis",1],["pasimetusiuose",1],["pasimetėlius",1],["pasimeškeriojęs",1],["pasimiegojus",1],["pasimiklinti",1],["pasimirk",1],["pasimirsiu",1],["pasimirta",1],["pasimirtų",1],["pasimirusiam",1],["pasimirusiojo",1],["pasimirusiųjų",1],["pasimirštančios",1],["pasimirštu",1],["pasimiršusi",1],["pasimistai",1],["pasimodavo",1],["pasimojavimo",1],["pasimojavom",1],["pasimokai",1],["pasimokantis",1],["pasimokinau",1],["pasimokinsi",1],["pasimokint",1],["pasimokinti",1],["pasimokinęs",1],["pasimokiusia",1],["pasimokiusiai",1],["pasimokiusiems",1],["pasimokiusius",1],["pasimokiusią",1],["pasimokom",1],["pasimokot",1],["pasimokydama",1],["pasimokydavau",1],["pasimokykim",1],["pasimokykit",1],["pasimokymo",1],["pasimokysim",1],["pasimokysiu",1],["pasimosikavęs",1],["pasimosuoja",1],["pasimovęs",1],["pasimoyti",1],["pasims",1],["pasimuistom",1],["pasimuistydavo",1],["pasimuistymas",1],["pasimuistymą",1],["pasimuisčius",1],["pasimulatinti",1],["pasimuliuoji",1],["pasimuliuočiau",1],["pasimurkdyti",1],["pasimušama",1],["pasimušdavo",1],["pasimuštų",1],["pasimyjėjusi",1],["pasimylavo",1],["pasimylinčios",1],["pasimylinčius",1],["pasimyluojame",1],["pasimyluosim",1],["pasimylėjimai",1],["pasimylėjote",1],["pasimylėjusioms",1],["pasimylėjusios",1],["pasimylėsianti",1],["pasimylėsite",1],["pasimylėta",1],["pasimylėtume",1],["pasimylėtumėte",1],["pasimėgaudavęs",1],["pasimėgaujantis",1],["pasimėgaukime",1],["pasimėgaus",1],["pasimėgausite",1],["pasimėgaut",1],["pasimėgauta",1],["pasimėgautumėt",1],["pasimėgavimai",1],["pasimėgavo",1],["pasimėgavote",1],["pasimėme",1],["pasimėtoma",1],["pasimėtusį",1],["pasimėtymas",1],["pasimėtymo",1],["pasimėtysi",1],["pasimųšti",1],["pasinaduoti",1],["pasinagrinėti",1],["pasinaikina",1],["pasinaikindavo",1],["pasinaikino",1],["pasinaikintų",1],["pasinaikinę",1],["pasinarsinam",1],["pasinaršius",1],["pasinaršęs",1],["pasinaudama",1],["pasinaudodamai",1],["pasinaudojam",1],["pasinaudojančio",1],["pasinaudojančiomis",1],["pasinaudojančios",1],["pasinaudojimui",1],["pasinaudojusiais",1],["pasinaudojusioms",1],["pasinaudojusią",1],["pasinaudojės",1],["pasinaudome",1],["pasinaudosiančios",1],["pasinaudosią",1],["pasinaudotum",1],["pasinauduodamos",1],["pasinauduoti",1],["pasinauti",1],["pasineigimą",1],["pasinerdamos",1],["pasinerdavote",1],["pasinerdavęs",1],["pasineriam",1],["pasineriantys",1],["pasineriančiais",1],["pasineriančią",1],["pasinerkim",1],["pasinersi",1],["pasinersiu",1],["pasinerta",1],["pasinertumei",1],["pasinervinsi",1],["pasines",1],["pasinesiklausinėjam",1],["pasinešdinti",1],["pasinešimo",1],["pasinešta",1],["pasineštum",1],["pasinešusiais",1],["pasinešusias",1],["pasinešusius",1],["pasinga",1],["pasingumas",1],["pasini",1],["pasiniai",1],["pasininkaujančioj",1],["pasinioti",1],["pasiniurkom",1],["pasinių",1],["pasinorėjau",1],["pasinuodijimo",1],["pasinėria",1],["pasinėrimui",1],["pasinėrimų",1],["pasinėrusia",1],["pasinėrusiu",1],["pasionariai",1],["pasionarijomis",1],["pasionarijum",1],["pasionarijų",1],["pasionariškumu",1],["pasionariškų",1],["pasiorganizuoja",1],["pasipainiodavome",1],["pasipainiodavę",1],["pasipainiojau",1],["pasipainiojusia",1],["pasipainiojusiai",1],["pasipainiojusiam",1],["pasipainiojusias",1],["pasipainiojusiu",1],["pasipainioję",1],["pasipainiotų",1],["pasipainojau",1],["pasipaplūdimiautojams",1],["pasipasakodama",1],["pasipasakodamas",1],["pasipasakojai",1],["pasipasakojama",1],["pasipasakojame",1],["pasipasakojantis",1],["pasipasakojate",1],["pasipasakojot",1],["pasipasakoju",1],["pasipasakokite",1],["pasipasakosim",1],["pasipasakota",1],["pasipasakočiau",1],["pasipelnijimui",1],["pasipelniusieji",1],["pasipelniusiems",1],["pasipelniusiųjų",1],["pasipelniusį",1],["pasipelnoma",1],["pasipelnydamas",1],["pasipelnydavę",1],["pasipelnymais",1],["pasipelnysi",1],["pasipelnysiantys",1],["pasiperia",1],["pasipešdavo",1],["pasipešdavome",1],["pasipešim",1],["pasipešinimai",1],["pasipešiojimas",1],["pasipešioti",1],["pasipiginome",1],["pasipiginti",1],["pasipiginu",1],["pasipiktimą",1],["pasipiktinama",1],["pasipiktinat",1],["pasipiktinimais",1],["pasipiktininą",1],["pasipiktinom",1],["pasipiktint",1],["pasipiktinu",1],["pasipiktinusioji",1],["pasipiktinusiomis",1],["pasipiktinusioms",1],["pasipiktinusią",1],["pasipiktinusiąją",1],["pasipiktiną",1],["pasipiktinės",1],["pasipilame",1],["pasipildai",1],["pasipildant",1],["pasipildantys",1],["pasipildančiomis",1],["pasipildančią",1],["pasipildome",1],["pasipildydama",1],["pasipildydamos",1],["pasipildydavome",1],["pasipildyk",1],["pasipildykime",1],["pasipildymu",1],["pasipina",1],["pasipinigaut",1],["pasipinigautojai",1],["pasipinigautoju",1],["pasipinigavimai",1],["pasipinigavimu",1],["pasipinigavimui",1],["pasipinigavimus",1],["pasipinigavusius",1],["pasipinigiavimas",1],["pasipiniguoti",1],["pasipirkite",1],["pasipiršdavo",1],["pasipiršimas",1],["pasipiršimo",1],["pasipiršimu",1],["pasipirškite",1],["pasipiršusi",1],["pasipiršusio",1],["pasipjauna",1],["pasipjaunam",1],["pasipjovimą",1],["pasipjovusio",1],["pasipjovėme",1],["pasipjovęs",1],["pasipjudymo",1],["pasiplakdami",1],["pasiplaks",1],["pasiplakti",1],["pasiplanuotas",1],["pasiplanuoti",1],["pasiplaukioja",1],["pasiplaukiojimai",1],["pasiplaukiojimu",1],["pasiplaukiojimui",1],["pasiplaukiojimus",1],["pasiplaukiojimų",1],["pasiplaukiok",1],["pasiplaukymas",1],["pasiplekšenimas",1],["pasiplekšnodami",1],["pasiplekšnoji",1],["pasiplekšnojimai",1],["pasiplekšnojom",1],["pasiplepėdami",1],["pasiplepėdamos",1],["pasiplepėdavo",1],["pasiplepėjimams",1],["pasiplepėjo",1],["pasiplepėsite",1],["pasiplepėtojai",1],["pasipliauškėdami",1],["pasipliekė",1],["pasipliuškenimui",1],["pasipliuškenimą",1],["pasipliuškeno",1],["pasipliuškenome",1],["pasipliuškenusios",1],["pasiplokime",1],["pasiploninęs",1],["pasiplosim",1],["pasiplėšiantys",1],["pasiplėšimas",1],["pasiplėšimą",1],["pasiplėšyti",1],["pasiplūkti",1],["pasiplūkęs",1],["pasiplūsti",1],["pasipomadavo",1],["pasipraktikavę",1],["pasipraktikuoja",1],["pasipraktikuosime",1],["pasipraktikuot",1],["pasipraktikuotų",1],["pasiprasčiokinimu",1],["pasipratinimo",1],["pasiprausimu",1],["pasiprašae",1],["pasiprašai",1],["pasiprašantis",1],["pasiprašiusia",1],["pasiprašiusio",1],["pasiprašiusiu",1],["pasiprašiusią",1],["pasiprašiusių",1],["pasiprašiusiųjų",1],["pasiprašiusį",1],["pasiprašomi",1],["pasiprašydama",1],["pasiprašyk",1],["pasiprašykim",1],["pasiprašykime",1],["pasiprašysi",1],["pasiprašysią",1],["pasiprašėm",1],["pasipreišino",1],["pasipriekaištaujame",1],["pasiprieęinimas",1],["pasiprieęinimo",1],["pasiprieši",1],["pasipriešinam",1],["pasipriešinama",1],["pasipriešinantį",1],["pasipriešinančia",1],["pasipriešindama",1],["pasipriešindamas",1],["pasipriešindamos",1],["pasipriešindavome",1],["pasipriešinimams",1],["pasipriešinimoxxvii",1],["pasipriešinimuose",1],["pasipriešininmo",1],["pasipriešinsią",1],["pasipriešinusioje",1],["pasipriešinusiojo",1],["pasipriešinusiuosius",1],["pasipriešinčiau",1],["pasiprivatizavęs",1],["pasiprivatizuoti",1],["pasiprūpins",1],["pasipudravimų",1],["pasipudravus",1],["pasipudravusi",1],["pasipudravusiai",1],["pasipudravusių",1],["pasipudravę",1],["pasipudruoja",1],["pasipudruok",1],["pasipuikavę",1],["pasipuikuodamas",1],["pasipuikuodami",1],["pasipuikuodavau",1],["pasipuikuok",1],["pasipuikuosiu",1],["pasipuikuotume",1],["pasipukšėdami",1],["pasipuokuoti",1],["pasipuošdavote",1],["pasipuošei",1],["pasipuoši",1],["pasipuošiant",1],["pasipuošianti",1],["pasipuošiančio",1],["pasipuošiančios",1],["pasipuošiančių",1],["pasipuošimas",1],["pasipuošimo",1],["pasipuošite",1],["pasipuošiusios",1],["pasipuoškime",1],["pasipuošta",1],["pasipuoštum",1],["pasipuošusiems",1],["pasipuošėm",1],["pasipuošį",1],["pasipurtau",1],["pasipurtydavo",1],["pasipurtymo",1],["pasipurtys",1],["pasipurškusi",1],["pasipurškęs",1],["pasipusto",1],["pasipustom",1],["pasipustome",1],["pasipustydavo",1],["pasipustykime",1],["pasipustykite",1],["pasipustys",1],["pasipustysi",1],["pasipustysiu",1],["pasipustysią",1],["pasipustę",1],["pasipusčiusi",1],["pasiputojo",1],["pasipučiu",1],["pasipykdavome",1],["pasipykstame",1],["pasipylusiais",1],["pasipylusias",1],["pasipylėm",1],["pasipynusius",1],["pasipynusį",1],["pasipynė",1],["pasipėrus",1],["pasipūs",1],["pasipūsi",1],["pasipūsti",1],["pasipūtei",1],["pasipūti",1],["pasipūtimai",1],["pasipūtusias",1],["pasipūtusioms",1],["pasipūtėle",1],["pasipūtėlei",1],["pasipūtėliui",1],["pasipūtėliško",1],["pasipūtėliškom",1],["pasipūtėlišku",1],["pasipūtėliškumas",1],["pasipūtėliškumą",1],["pasipūtėlišką",1],["pasipūčia",1],["pasipūčiau",1],["pasira",1],["pasiraginimas",1],["pasiraginimo",1],["pasiragino",1],["pasiraitojam",1],["pasiraitoju",1],["pasiraitojusią",1],["pasiraitojusių",1],["pasiraitokim",1],["pasiraitokite",1],["pasiraitos",1],["pasiraitot",1],["pasiraitydavo",1],["pasiraityk",1],["pasiraitys",1],["pasiraitė",1],["pasiraivo",1],["pasiraičiau",1],["pasiraičiojo",1],["pasiraičiusi",1],["pasiraminimai",1],["pasiramstydami",1],["pasiramstydamos",1],["pasiramstyt",1],["pasiramstė",1],["pasiramsčiuodamos",1],["pasiramsčiuodavo",1],["pasiramsčiuojamas",1],["pasiramsčiuojantis",1],["pasiramsčiuojantys",1],["pasiramsčiuojančius",1],["pasiramsčiuojančių",1],["pasiramščiuodama",1],["pasirangyti",1],["pasirangę",1],["pasirangęs",1],["pasirankioja",1],["pasirankiojimas",1],["pasirankiojimu",1],["pasirankiojo",1],["pasirankiotų",1],["pasirasyti",1],["pasiraudodama",1],["pasiraukdavo",1],["pasirauks",1],["pasiraukydavo",1],["pasiraukyti",1],["pasiraukė",1],["pasiraukšlėjusias",1],["pasirausdavo",1],["pasirausiau",1],["pasirauskim",1],["pasiraususi",1],["pasiraususios",1],["pasirausvinu",1],["pasirausėme",1],["pasiraut",1],["pasiraõyti",1],["pasiraõó",1],["pasiraęytas",1],["pasiraęė",1],["pasirašantiesiems",1],["pasirašantysis",1],["pasirašantį",1],["pasirašančią",1],["pasiraši",1],["pasirašiai",1],["pasirašinėdama",1],["pasirašinėdavau",1],["pasirašinėdavęs",1],["pasirašinėjai",1],["pasirašinėjantiems",1],["pasirašinėjantys",1],["pasirašinėjančiam",1],["pasirašinėjate",1],["pasirašinėjom",1],["pasirašinėjome",1],["pasirašinėjusia",1],["pasirašinėsim",1],["pasirašinėtas",1],["pasirašinėtos",1],["pasirašinėtų",1],["pasirašiusioje",1],["pasirašiusioji",1],["pasirašiusiosios",1],["pasirašiusysis",1],["pasirašiusįjį",1],["pasiraškyti",1],["pasirašomai",1],["pasirašomo",1],["pasirašomoji",1],["pasirašomosne",1],["pasirašomu",1],["pasirašomuose",1],["pasirašot",1],["pasirašta",1],["pasirašti",1],["pasiraštyti",1],["pasirašusi",1],["pasirašy",1],["pasirašyc",1],["pasirašydavom",1],["pasirašydinau",1],["pasirašymams",1],["pasirašymuose",1],["pasirašysit",1],["pasirašytina",1],["pasirašytinas",1],["pasirašytini",1],["pasirašyts",1],["pasirašytumėm",1],["pasirašą",1],["pasirašąs",1],["pasirašėmė",1],["pasirebgęs",1],["pasirebkamuosius",1],["pasiregimą",1],["pasiregti",1],["pasireiksiančiomis",1],["pasireikšdavome",1],["pasireikšdavusi",1],["pasireikšdavęs",1],["pasireikšiančiomis",1],["pasireikšite",1],["pasireikšk",1],["pasireikšt",1],["pasireikštume",1],["pasireiõkia",1],["pasireiõkus",1],["pasireiõkņs",1],["pasireiękia",1],["pasireiįkianti",1],["pasireiškiame",1],["pasireiškiančiame",1],["pasireiškianęios",1],["pasireiškiu",1],["pasireiškti",1],["pasireiškusiais",1],["pasireiškusiam",1],["pasireiškusieji",1],["pasireiškusioje",1],["pasireiškusisi",1],["pasireišė",1],["pasirekamaisiais",1],["pasirekame",1],["pasireklamavęs",1],["pasireklamuodavo",1],["pasiremiame",1],["pasiremiantis",1],["pasiremontavimui",1],["pasiremontavimą",1],["pasiremontuosiu",1],["pasiremontuot",1],["pasiremontuotais",1],["pasiremt",1],["pasiremtų",1],["pasirengdamas",1],["pasirengdavome",1],["pasirengei",1],["pasirengiamasis",1],["pasirengiamo",1],["pasirengiamuoju",1],["pasirengiantis",1],["pasirengiantį",1],["pasirengimais",1],["pasirengimams",1],["pasirengimopačiai",1],["pasirengimųrusai",1],["pasirenginas",1],["pasirengsi",1],["pasirengsianti",1],["pasirengsui",1],["pasirengtais",1],["pasirengtos",1],["pasirengtyje",1],["pasirengtą",1],["pasirengusioje",1],["pasirengęsa",1],["pasirenkamam",1],["pasirenkamasvakarų",1],["pasirenkamiesiems",1],["pasirenkamumas",1],["pasirenkamumu",1],["pasirenkamumą",1],["pasirenkamąją",1],["pasirenkamąsias",1],["pasirenkantį",1],["pasirenkančia",1],["pasirenkančiai",1],["pasirenkančiam",1],["pasirenkančioje",1],["pasirenkančiomis",1],["pasirenkat",1],["pasirenkim",1],["pasirenkime",1],["pasirenkąs",1],["pasirenmamiems",1],["pasirepetuoti",1],["pasirepečkinęs",1],["pasireškė",1],["pasirguliuoja",1],["pasirgusi",1],["pasirgęs",1],["pasiriejo",1],["pasirieti",1],["pasirietusias",1],["pasirikimo",1],["pasiriko",1],["pasirin",1],["pasiriniko",1],["pasirinimo",1],["pasirinka",1],["pasirinkcie",1],["pasirinkdavusi",1],["pasirinkims",1],["pasirinkinkti",1],["pasirinkinmo",1],["pasirinkino",1],["pasirinkintos",1],["pasirinkinėja",1],["pasirinkiti",1],["pasirinksiantiems",1],["pasirinksiančių",1],["pasirinksit",1],["pasirinksią",1],["pasirinksiąs",1],["pasirinktines",1],["pasirinktinio",1],["pasirinktiniu",1],["pasirinktiniški",1],["pasirinktinių",1],["pasirinktinos",1],["pasirinktiną",1],["pasirinktinį",1],["pasirinktis",1],["pasirinktoj",1],["pasirinktom",1],["pasirinkton",1],["pasirinktumei",1],["pasirinktõs",1],["pasirinktį",1],["pasirinkusiame",1],["pasirinkusioje",1],["pasirinkusiose",1],["pasirinkusiuose",1],["pasirinkusiuosius",1],["pasirinkėjo",1],["pasirinkėją",1],["pasirinta",1],["pasirintosios",1],["pasirintume",1],["pasirinus",1],["pasiristi",1],["pasiritusį",1],["pasirišamas",1],["pasirišdama",1],["pasirišk",1],["pasiriškiančią",1],["pasirišom",1],["pasirištu",1],["pasirišus",1],["pasirišusiai",1],["pasirišusios",1],["pasiriūriu",1],["pasirnkti",1],["pasirod",1],["pasirodantieji",1],["pasirodantysis",1],["pasirodančiai",1],["pasirodančiame",1],["pasirodančiųjų",1],["pasiroddymų",1],["pasirodiusį",1],["pasirodydavusi",1],["pasirodydavusią",1],["pasirodykim",1],["pasirodykit",1],["pasirodyma",1],["pasirodymnas",1],["pasirodysiančia",1],["pasirodysiančiuose",1],["pasirodystrys",1],["pasirodytai",1],["pasirodytiti",1],["pasirodytumėt",1],["pasirodytumėte",1],["pasirodą",1],["pasirodčs",1],["pasirodėlietuvoje",1],["pasirodėė",1],["pasirogys",1],["pasirokavimo",1],["pasirokavusi",1],["pasirokouti",1],["pasirokuo",1],["pasirokuodavo",1],["pasirokuojama",1],["pasirokuot",1],["pasiropinėjimai",1],["pasirošęs",1],["pasirpinimo",1],["pasirtikrinti",1],["pasirungs",1],["pasirungsime",1],["pasirungė",1],["pasirunsiu",1],["pasiruošdamas",1],["pasiruošdami",1],["pasiruošes",1],["pasiruošfs",1],["pasiruošiamasis",1],["pasiruošiami",1],["pasiruošiamąjį",1],["pasiruošianti",1],["pasiruošiančių",1],["pasiruošiate",1],["pasiruošima",1],["pasiruošimais",1],["pasiruošite",1],["pasiruošiusieji",1],["pasiruošiusių",1],["pasiruoštame",1],["pasiruoštomis",1],["pasiruoštos",1],["pasiruoštu",1],["pasiruoštum",1],["pasiruoštumėte",1],["pasiruošusioje",1],["pasiruošusiomis",1],["pasirušimo",1],["pasiryškink",1],["pasiryštų",1],["pasirómus",1],["pasirėdei",1],["pasirėdius",1],["pasirėdo",1],["pasirėdydavo",1],["pasirėdyk",1],["pasirėdymas",1],["pasirėdymo",1],["pasirėdyti",1],["pasirėdė",1],["pasirėmimu",1],["pasirėmimą",1],["pasirėmusiais",1],["pasirėmusiu",1],["pasirėmėm",1],["pasirįš",1],["pasiršė",1],["pasirūgštyniauti",1],["pasirūkinkime",1],["pasirūpinai",1],["pasirūpinanti",1],["pasirūpinančias",1],["pasirūpindavau",1],["pasirūpindavome",1],["pasirūpindavę",1],["pasirūpinimais",1],["pasirūpinimą",1],["pasirūpinsianti",1],["pasirūpinsiantį",1],["pasirūpinsią",1],["pasirūpintis",1],["pasirūpintum",1],["pasirūpintumėme",1],["pasirūpintumėt",1],["pasirūpintumėte",1],["pasirūpinusiai",1],["pasirūpinusiam",1],["pasirūpinusieji",1],["pasirūpinusio",1],["pasisakaes",1],["pasisakaityti",1],["pasisakančiais",1],["pasisakančiojo",1],["pasisakiantys",1],["pasisakinėjęs",1],["pasisakinėti",1],["pasisakiusia",1],["pasisakiusiai",1],["pasisakiusios",1],["pasisakiusiu",1],["pasisakiųsiųjų",1],["pasisakmbinti",1],["pasisakydavai",1],["pasisakysit",1],["pasisakyt",1],["pasisakytumėte",1],["pasisaldina",1],["pasisaldinkit",1],["pasisaldinsi",1],["pasisaldintum",1],["pasisaldinus",1],["pasisamdai",1],["pasisamdau",1],["pasisamdydavau",1],["pasisamdykime",1],["pasisamdysiu",1],["pasisamdyt",1],["pasisamdytas",1],["pasisamdytos",1],["pasisamdytume",1],["pasisamdytą",1],["pasisamdyčiau",1],["pasisarmatys",1],["pasisaugo",1],["pasisaugodamas",1],["pasisaugodavo",1],["pasisaugojo",1],["pasisaugoki",1],["pasisaugokit",1],["pasisaugot",1],["pasisaugotume",1],["pasisaugąs",1],["pasisavimą",1],["pasisavinamam",1],["pasisavinamojo",1],["pasisavinamu",1],["pasisavinantieji",1],["pasisavindavęs",1],["pasisavinimais",1],["pasisavinimus",1],["pasisavinkime",1],["pasisavinom",1],["pasisavinome",1],["pasisavinsime",1],["pasisavintam",1],["pasisavintoja",1],["pasisavintojų",1],["pasisavintomis",1],["pasisavintum",1],["pasisavintume",1],["pasisavintųjų",1],["pasisavinusiai",1],["pasisavinusiais",1],["pasisavinusioje",1],["pasisavinusiu",1],["pasisavinusiųjų",1],["pasisavinąs",1],["pasisavo",1],["pasisavyt",1],["pasisedėjo",1],["pasiseilėjimus",1],["pasisekančio",1],["pasisekime",1],["pasisekimuose",1],["pasiseksią",1],["pasisekusiais",1],["pasisekusiomis",1],["pasisekusius",1],["pasisekusį",1],["pasisemdama",1],["pasisemdami",1],["pasisemdavau",1],["pasisemdavome",1],["pasisemdavę",1],["pasisemiami",1],["pasisemkit",1],["pasisemtais",1],["pasisemtame",1],["pasisemto",1],["pasisemtus",1],["pasisemčiau",1],["pasisendinau",1],["pasisendino",1],["pasisendinęs",1],["pasisenk",1],["pasisiautusi",1],["pasisiekdavo",1],["pasisieki",1],["pasisiekia",1],["pasisiekimą",1],["pasisiekti",1],["pasisiekusi",1],["pasisiekčiau",1],["pasisiekė",1],["pasisielojo",1],["pasisikęs",1],["pasisiosi",1],["pasisioti",1],["pasisiskirstymo",1],["pasisitatę",1],["pasisitengęs",1],["pasisiurbčiodami",1],["pasisiuvus",1],["pasisiuvęs",1],["pasisiūbavimai",1],["pasisiūdamas",1],["pasisiūdinau",1],["pasisiūdinkite",1],["pasisiūdins",1],["pasisiūdintais",1],["pasisiūdinto",1],["pasisiūdintomis",1],["pasisiūdinusiam",1],["pasisiūkim",1],["pasisiūlantis",1],["pasisiūlančiam",1],["pasisiūlančių",1],["pasisiūlei",1],["pasisiūlome",1],["pasisiūlydama",1],["pasisiūlydamas",1],["pasisiūlyk",1],["pasisiūlymus",1],["pasisiūlymų",1],["pasisiūlysiu",1],["pasisiūlyčiau",1],["pasisiūna",1],["pasisiūs",1],["pasisiūsim",1],["pasisiūsinimais",1],["pasisiūsite",1],["pasisiūt",1],["pasisiūta",1],["pasisiūtais",1],["pasisiūtame",1],["pasisiūtas",1],["pasisiūto",1],["pasisiūtu",1],["pasisiūtus",1],["pasisiūtą",1],["pasisiūtų",1],["pasisiūvo",1],["pasiskabęs",1],["pasiskaidė",1],["pasiskaidę",1],["pasiskaistinusi",1],["pasiskaitant",1],["pasiskaitote",1],["pasiskaity",1],["pasiskaitydamas",1],["pasiskaitydavome",1],["pasiskaitymais",1],["pasiskaitymu",1],["pasiskaitymėliai",1],["pasiskaitymėlio",1],["pasiskaitysite",1],["pasiskaitysiąs",1],["pasiskaitytas",1],["pasiskaitytume",1],["pasiskaitytumėt",1],["pasiskaityčiau",1],["pasiskaičiavote",1],["pasiskaičiavęs",1],["pasiskaičiuodavo",1],["pasiskaičiuojant",1],["pasiskaičiuokime",1],["pasiskaičiuosiu",1],["pasiskaičiusi",1],["pasiskaičiusios",1],["pasiskaldymo",1],["pasiskaldę",1],["pasiskambins",1],["pasiskambinusios",1],["pasiskambinę",1],["pasiskanaudamas",1],["pasiskanaudami",1],["pasiskandalino",1],["pasiskandinimą",1],["pasiskandino",1],["pasiskandins",1],["pasiskardena",1],["pasiskardenimai",1],["pasiskardeno",1],["pasiskelbdavo",1],["pasiskelbk",1],["pasiskelbsiančių",1],["pasiskelbsime",1],["pasiskelbtum",1],["pasiskelbtume",1],["pasiskelbusiai",1],["pasiskelbusias",1],["pasiskelbusiesiems",1],["pasiskelbusius",1],["pasiskeryčiojimų",1],["pasiskeryčiosi",1],["pasiskeryčioti",1],["pasiskes",1],["pasiskiepijant",1],["pasiskiepijimo",1],["pasiskiepijome",1],["pasiskiepijote",1],["pasiskiepijusi",1],["pasiskiepijusiai",1],["pasiskiepijusiam",1],["pasiskiepijusio",1],["pasiskiepino",1],["pasiskiepykime",1],["pasiskiepykite",1],["pasiskiepytų",1],["pasiskindavo",1],["pasiskins",1],["pasiskinsim",1],["pasiskirdami",1],["pasiskiri",1],["pasiskiriamus",1],["pasiskiriant",1],["pasiskiriančios",1],["pasiskirstanti",1],["pasiskirstančios",1],["pasiskirstančių",1],["pasiskirstimu",1],["pasiskirstomi",1],["pasiskirstomos",1],["pasiskirstydama",1],["pasiskirstydamos",1],["pasiskirstydavom",1],["pasiskirstydavome",1],["pasiskirstykite",1],["pasiskirstymų",1],["pasiskirstytas",1],["pasiskirstytume",1],["pasiskirstytumėte",1],["pasiskirstėm",1],["pasiskirsčiusiems",1],["pasiskirsčiusius",1],["pasiskirt",1],["pasiskirta",1],["pasiskirtu",1],["pasiskirtumėt",1],["pasiskirtymas",1],["pasiskirtymo",1],["pasiskirčiau",1],["pasiskirčius",1],["pasiskirčiusi",1],["pasisklaido",1],["pasisklaidymą",1],["pasiskleidimą",1],["pasiskleidus",1],["pasiskleidusios",1],["pasiskleis",1],["pasiskolinamų",1],["pasiskolinant",1],["pasiskolinančio",1],["pasiskolinate",1],["pasiskolindamos",1],["pasiskolindavom",1],["pasiskolinimais",1],["pasiskolinimas",1],["pasiskolinimą",1],["pasiskolinsim",1],["pasiskolinsime",1],["pasiskolintai",1],["pasiskolintam",1],["pasiskolintame",1],["pasiskolintasis",1],["pasiskolintoje",1],["pasiskolintąją",1],["pasiskolintąjį",1],["pasiskolinusiose",1],["pasiskolinusį",1],["pasiskonėdamas",1],["pasiskraidymų",1],["pasiskraidyti",1],["pasiskristymo",1],["pasiskristymą",1],["pasiskristę",1],["pasiskubink",1],["pasiskubinome",1],["pasiskubins",1],["pasiskubintis",1],["pasiskubintų",1],["pasiskubinusi",1],["pasiskubinusių",1],["pasiskubinę",1],["pasiskubinęs",1],["pasiskundimai",1],["pasiskundimo",1],["pasiskundimą",1],["pasiskundusiai",1],["pasiskundusiajam",1],["pasiskundusiam",1],["pasiskundusios",1],["pasiskundusiuoju",1],["pasiskundės",1],["pasiskundėte",1],["pasiskynusios",1],["pasiskynė",1],["pasiskyrstymas",1],["pasiskyrstė",1],["pasiskyrusiai",1],["pasiskyrusiam",1],["pasiskųsdama",1],["pasiskųsdamas",1],["pasiskųsdavau",1],["pasiskųsim",1],["pasiskųsk",1],["pasiskųsčiau",1],["pasislampinėjimai",1],["pasislapstyk",1],["pasislapstė",1],["pasislapstęs",1],["pasislenkame",1],["pasislenkantys",1],["pasislenku",1],["pasislepiantys",1],["pasislepiančios",1],["pasislepiančius",1],["pasislepiate",1],["pasislikti",1],["pasislinkdama",1],["pasislinkim",1],["pasislinkimu",1],["pasislinkimų",1],["pasislinkite",1],["pasislinkmas",1],["pasislinkome",1],["pasislinkta",1],["pasislinktum",1],["pasislinkusiame",1],["pasislinkusiu",1],["pasislinkusiųjų",1],["pasislėpda",1],["pasislėpdamos",1],["pasislėpdavom",1],["pasislėpdavome",1],["pasislėpei",1],["pasislėpimo",1],["pasislėpkim",1],["pasislėpkite",1],["pasislėpsianti",1],["pasislėpsiąs",1],["pasislėptum",1],["pasislėptumėt",1],["pasislėptumėte",1],["pasislėpusia",1],["pasislėpusioje",1],["pasislėpusiomis",1],["pasislėpusiųjų",1],["pasislėpėlėms",1],["pasislėpėt",1],["pasismagina",1],["pasismaginau",1],["pasismagindama",1],["pasismaginimus",1],["pasismagino",1],["pasismaginome",1],["pasismagins",1],["pasismaginęs",1],["pasismailink",1],["pasismailino",1],["pasismailinti",1],["pasismailinusi",1],["pasismaugsim",1],["pasismaugta",1],["pasismaugtume",1],["pasismaugusi",1],["pasismaugusiam",1],["pasismaukyti",1],["pasismaukęs",1],["pasismeigia",1],["pasismeigiau",1],["pasismeigs",1],["pasismeigsi",1],["pasismeigti",1],["pasismerkimas",1],["pasismerkimo",1],["pasismeti",1],["pasismilkymui",1],["pasismiolka",1],["pasisoden",1],["pasisodiname",1],["pasisodinate",1],["pasisodindami",1],["pasisodindavau",1],["pasisodini",1],["pasisodinkit",1],["pasisodinote",1],["pasisodinsianti",1],["pasisodintum",1],["pasisodinčiau",1],["pasisodys",1],["pasisodzina",1],["pasisodzino",1],["pasisonk",1],["pasisotiname",1],["pasisotinate",1],["pasisotinau",1],["pasisotindama",1],["pasisotinimai",1],["pasisotinkite",1],["pasisotinsiančios",1],["pasisotinsim",1],["pasisotinsime",1],["pasisotintum",1],["pasisotintume",1],["pasisotintų",1],["pasisotinu",1],["pasisotinusi",1],["pasisotinusio",1],["pasispardant",1],["pasispardei",1],["pasispardo",1],["pasispardydami",1],["pasispardymais",1],["pasispardymu",1],["pasispardymui",1],["pasispardymus",1],["pasispardymą",1],["pasispardysi",1],["pasispardyt",1],["pasispardytų",1],["pasispardzydama",1],["pasispardė",1],["pasispardęs",1],["pasispaudus",1],["pasispaudė",1],["pasispaudėm",1],["pasispaudęs",1],["pasispaus",1],["pasispausdavau",1],["pasispausi",1],["pasispaust",1],["pasispirdama",1],["pasispirdami",1],["pasispiri",1],["pasispiria",1],["pasispiriu",1],["pasispirk",1],["pasispirti",1],["pasispjaudydami",1],["pasispjaudyk",1],["pasispjaudymais",1],["pasispjaudyti",1],["pasispjaudė",1],["pasispjaudęs",1],["pasispragina",1],["pasispraudęs",1],["pasisprengsėdamas",1],["pasispriešinimai",1],["pasispygavimais",1],["pasispyrioja",1],["pasispyriojau",1],["pasispyriojo",1],["pasispyrios",1],["pasispyruokliuoja",1],["pasispyrusi",1],["pasispęsti",1],["pasisriūbaujant",1],["pasisrėbti",1],["pasissekė",1],["pasistaipiau",1],["pasistaipymą",1],["pasistatanti",1],["pasistatom",1],["pasistatote",1],["pasistatydama",1],["pasistatydami",1],["pasistatydavęs",1],["pasistatydinamos",1],["pasistatydinom",1],["pasistatydinome",1],["pasistatydins",1],["pasistatydintame",1],["pasistatydinusi",1],["pasistatydinęs",1],["pasistatymui",1],["pasistatysit",1],["pasistatytidinti",1],["pasistatytumėm",1],["pasistatėt",1],["pasistačiusia",1],["pasistačiusio",1],["pasistačiusiu",1],["pasistačiusią",1],["pasistačiusiųjų",1],["pasistebdavo",1],["pasistebint",1],["pasistebėdavo",1],["pasistebėjau",1],["pasistebėjo",1],["pasistebėjusi",1],["pasistebėję",1],["pasistebėjęs",1],["pasisteisino",1],["pasisteisinti",1],["pasistempęs",1],["pasistengdamas",1],["pasistengdamos",1],["pasistengdavai",1],["pasistengei",1],["pasistengiant",1],["pasistengiantys",1],["pasistengisme",1],["pasistengtinugalėti",1],["pasistengtumėme",1],["pasistengėte",1],["pasistenkim",1],["pasistenkinte",1],["pasistiebdavo",1],["pasistiebusiu",1],["pasistiebusių",1],["pasistiepk",1],["pasistiepusios",1],["pasistiepė",1],["pasistimuliuotum",1],["pasistipriname",1],["pasistiprindamas",1],["pasistiprindavo",1],["pasistiprinimas",1],["pasistiprinimo",1],["pasistiprinimui",1],["pasistiprinkime",1],["pasistiprinom",1],["pasistiprinome",1],["pasistiprins",1],["pasistiprinsime",1],["pasistiprint",1],["pasistiprinta",1],["pasistiprinu",1],["pasistngti",1],["pasistodavo",1],["pasistojam",1],["pasistoji",1],["pasistojus",1],["pasistojusiais",1],["pasistojusiu",1],["pasistos",1],["pasistoti",1],["pasistoviniavau",1],["pasistovėjimui",1],["pasistovėjome",1],["pasistraksėdama",1],["pasistrykčiodama",1],["pasistrykčiodamas",1],["pasistumdama",1],["pasistumdamas",1],["pasistumdantis",1],["pasistumdydamos",1],["pasistumdymais",1],["pasistumdymą",1],["pasistumdysi",1],["pasistumdyta",1],["pasistumdę",1],["pasistumdęs",1],["pasistumiu",1],["pasistumk",1],["pasistumti",1],["pasistumtų",1],["pasistumėta",1],["pasistvėriau",1],["pasistypčiodamas",1],["pasistūmimą",1],["pasistūmusi",1],["pasistūmusiais",1],["pasistūmėdama",1],["pasistūmėjimai",1],["pasistūmėjote",1],["pasistūmėjusiais",1],["pasistūmėjusiuosius",1],["pasistūmėtum",1],["pasistūmę",1],["pasistūmęs",1],["pasisukame",1],["pasisukantis",1],["pasisukančios",1],["pasisukančius",1],["pasisukančių",1],["pasisukat",1],["pasisukdama",1],["pasisukdavome",1],["pasisukimuos",1],["pasisukimus",1],["pasisukinėdavo",1],["pasisukinėjimai",1],["pasisukinėjusiam",1],["pasisukinėk",1],["pasisukinėkime",1],["pasisukiodavo",1],["pasisukioja",1],["pasisukiojimas",1],["pasisukiojimų",1],["pasisukioju",1],["pasisukiojus",1],["pasisukiojusio",1],["pasisukioję",1],["pasisukiokim",1],["pasisukiotų",1],["pasisuktum",1],["pasisuktume",1],["pasisukusiam",1],["pasisukusio",1],["pasisukčiau",1],["pasisupa",1],["pasisupdamas",1],["pasisupimas",1],["pasisupkite",1],["pasisupom",1],["pasisupsi",1],["pasisupsiu",1],["pasisupu",1],["pasisupus",1],["pasisupčiau",1],["pasisupę",1],["pasisupęs",1],["pasisvaidoma",1],["pasisvaidymas",1],["pasisvaidymus",1],["pasisvaidyti",1],["pasisvaičiojimų",1],["pasisvei",1],["pasisveikindavai",1],["pasisveikinime",1],["pasisveikinkime",1],["pasisveikinsime",1],["pasisveikinta",1],["pasisveikintume",1],["pasisveikinusį",1],["pasisveikinčiau",1],["pasisvečiavimai",1],["pasisvečiavimui",1],["pasisvečiavimą",1],["pasisvečiavus",1],["pasisvečiavusios",1],["pasisvečiavusių",1],["pasisvečiavusį",1],["pasisvečiuoja",1],["pasisvečiuojame",1],["pasisvečiuoji",1],["pasisvečiuoju",1],["pasisvečiuokim",1],["pasisvečiuosite",1],["pasisvečiuotumėte",1],["pasisvečiuotų",1],["pasisvečiuočiau",1],["pasisvingavimas",1],["pasisvėriau",1],["pasisvėrusių",1],["pasisvėrė",1],["pasisvėrę",1],["pasisvėręs",1],["pasisėdami",1],["pasisėdim",1],["pasisėdjo",1],["pasisėdėdavome",1],["pasisėdėjimais",1],["pasisėdėję",1],["pasisėdėt",1],["pasisėju",1],["pasisėjus",1],["pasisėjusi",1],["pasisėjusiems",1],["pasisėjusią",1],["pasisėjusių",1],["pasisėmimo",1],["pasisėmusios",1],["pasisėmėm",1],["pasisėpiau",1],["pasisėt",1],["pasisėtiems",1],["pasisėtume",1],["pasisūdo",1],["pasisūdyti",1],["pasisūlai",1],["pasisūliau",1],["pasisūlė",1],["pasisūpuodama",1],["pasisūpuodamas",1],["pasisūpuokite",1],["pasitaika",1],["pasitaikantysis",1],["pasitaikančiose",1],["pasitaikančiosios",1],["pasitaikančiųjų",1],["pasitaikiančius",1],["pasitaikink",1],["pasitaikiusiems",1],["pasitaikiusioj",1],["pasitaikiusiojo",1],["pasitaikiusiomis",1],["pasitaikomąjį",1],["pasitaikydavusi",1],["pasitaikydavusių",1],["pasitaikydavęs",1],["pasitaikysianti",1],["pasitaikysiančios",1],["pasitaikó",1],["pasitaikąs",1],["pasitaisai",1],["pasitaisantiems",1],["pasitaisiusius",1],["pasitaisiusią",1],["pasitaisiusį",1],["pasitaisoma",1],["pasitaisykite",1],["pasitaisymai",1],["pasitaisymais",1],["pasitaisymu",1],["pasitaisysiant",1],["pasitaisysianti",1],["pasitaisysim",1],["pasitaisysite",1],["pasitaisytu",1],["pasitaisytum",1],["pasitaisyčiau",1],["pasitaisėm",1],["pasitaisėme",1],["pasitako",1],["pasitakozės",1],["pasitampai",1],["pasitampydavo",1],["pasitampyti",1],["pasitampėme",1],["pasitamsino",1],["pasitapšnos",1],["pasitarauti",1],["pasitardama",1],["pasitardavom",1],["pasitariam",1],["pasitariimas",1],["pasitarkim",1],["pasitarkuokite",1],["pasitarnaudamos",1],["pasitarnaujam",1],["pasitarnaujame",1],["pasitarnaujant",1],["pasitarnaujantys",1],["pasitarnaujančiu",1],["pasitarnauju",1],["pasitarnausiantis",1],["pasitarnausiančias",1],["pasitarnausime",1],["pasitarnausią",1],["pasitarnautume",1],["pasitarnautumėt",1],["pasitarnaučiau",1],["pasitarnavome",1],["pasitarnavote",1],["pasitarnavus",1],["pasitarnavusi",1],["pasitarnavusio",1],["pasitarnavusios",1],["pasitarnavusiu",1],["pasitarnavusių",1],["pasitarsi",1],["pasitarsit",1],["pasitarsią",1],["pasitartumei",1],["pasitartumėte",1],["pasitarukus",1],["pasitarukė",1],["pasitarusių",1],["pasitarusiųjų",1],["pasitarėte",1],["pasitaršiusiais",1],["pasitaupau",1],["pasitaupius",1],["pasitaupiusios",1],["pasitaupom",1],["pasitaupyk",1],["pasitaupėm",1],["pasitausojusiųjų",1],["pasitausokim",1],["pasitavęs",1],["pasitaškai",1],["pasitaškymas",1],["pasitaškymui",1],["pasitaškė",1],["pasitaškę",1],["pasitei",1],["pasiteikimą",1],["pasiteiko",1],["pasiteiraudama",1],["pasiteiraudamas",1],["pasiteiraudamos",1],["pasiteiraudavę",1],["pasiteiraujam",1],["pasiteiraujate",1],["pasiteiraukime",1],["pasiteirausiąs",1],["pasiteiraut",1],["pasiteirautume",1],["pasiteirautumėt",1],["pasiteirautumėte",1],["pasiteiravimus",1],["pasiteiravom",1],["pasiteiravote",1],["pasiteiravusio",1],["pasiteiravusios",1],["pasiteisinančia",1],["pasiteisindavau",1],["pasiteisini",1],["pasiteisinome",1],["pasiteisinsite",1],["pasiteisinsiu",1],["pasiteisinusiais",1],["pasiteisinčiau",1],["pasiteklti",1],["pasitekta",1],["pasitekti",1],["pasitekus",1],["pasitelike",1],["pasiteliuškuoja",1],["pasitelkdavau",1],["pasitelkdavusios",1],["pasitelkiam",1],["pasitelkiamus",1],["pasitelkiamą",1],["pasitelkianti",1],["pasitelkiantys",1],["pasitelkiančiai",1],["pasitelkiančią",1],["pasitelkiančių",1],["pasitelkim",1],["pasitelkimu",1],["pasitelkit",1],["pasitelksią",1],["pasitelktais",1],["pasitelktiems",1],["pasitelktinas",1],["pasitelkto",1],["pasitelktus",1],["pasitelktą",1],["pasitelkuios",1],["pasitelkusioms",1],["pasitelkėte",1],["pasitelkņ",1],["pasitemp",1],["pasitempdavo",1],["pasitempdavom",1],["pasitempiama",1],["pasitempiamas",1],["pasitempiančios",1],["pasitempimai",1],["pasitempimu",1],["pasitempkite",1],["pasitempsim",1],["pasitempt",1],["pasitempusiam",1],["pasitempusiu",1],["pasitempėme",1],["pasitengs",1],["pasitengė",1],["pasitenk",1],["pasitenkinanti",1],["pasitenkinančiais",1],["pasitenkinančiam",1],["pasitenkinančius",1],["pasitenkinančių",1],["pasitenkindavęs",1],["pasitenkinimai",1],["pasitenkinote",1],["pasitenkinsim",1],["pasitenkint",1],["pasitenkintyi",1],["pasitenkinusias",1],["pasitenkinusių",1],["pasitenkinąs",1],["pasitenkite",1],["pasitepdavo",1],["pasitepi",1],["pasitepimas",1],["pasitepsi",1],["pasiteptumėte",1],["pasiterime",1],["pasiteriojimas",1],["pasiterkite",1],["pasiterlioja",1],["pasiterlioję",1],["pasiti",1],["pasitiekia",1],["pasities",1],["pasitiesdavo",1],["pasitiesi",1],["pasitiesiam",1],["pasitiesim",1],["pasitiesiu",1],["pasitiesią",1],["pasitieskime",1],["pasitieskite",1],["pasitiesusias",1],["pasitikdavusios",1],["pasitikdavusį",1],["pasitikdavęs",1],["pasitikintieji",1],["pasitikinčiuosius",1],["pasitikinčiųjų",1],["pasitikinėti",1],["pasitikit",1],["pasitikiėjimo",1],["pasitikot",1],["pasitikrinai",1],["pasitikrinate",1],["pasitikrindami",1],["pasitikrindavome",1],["pasitikrindavot",1],["pasitikrinimai",1],["pasitikrinimus",1],["pasitikrinkim",1],["pasitikrinkit",1],["pasitikrinom",1],["pasitikrinote",1],["pasitikrinsi",1],["pasitikrinsianti",1],["pasitikrinsite",1],["pasitikrintas",1],["pasitikrinusieji",1],["pasitikrinusiems",1],["pasitikrinusiu",1],["pasitikrinusius",1],["pasitiksianti",1],["pasitiksiantis",1],["pasitiksiantys",1],["pasitikslinamas",1],["pasitikslinant",1],["pasitikslinate",1],["pasitikslini",1],["pasitikslintas",1],["pasitikslintų",1],["pasitikslinusios",1],["pasitiktavo",1],["pasitiktiniais",1],["pasitiktinių",1],["pasitiktinti",1],["pasitiktumėm",1],["pasitikusiais",1],["pasitikusieji",1],["pasitikusiu",1],["pasitikėdavai",1],["pasitikėdavę",1],["pasitikėhjęs",1],["pasitikėjimai",1],["pasitikėjimais",1],["pasitikėjusio",1],["pasitikėjusioms",1],["pasitikėjusios",1],["pasitikėjusių",1],["pasitikėjusį",1],["pasitikėkim",1],["pasitikėkit",1],["pasitikėsim",1],["pasitikėtimu",1],["pasitinkantiesiems",1],["pasitinkančiai",1],["pasitinkančiais",1],["pasitinkančiam",1],["pasitinkančioje",1],["pasitinkančiojo",1],["pasitinkančioms",1],["pasitinki",1],["pasitinkimas",1],["pasitinką",1],["pasitiėjimo",1],["pasitobulindavau",1],["pasitobulinimui",1],["pasitobulinom",1],["pasitobulins",1],["pasitobulinus",1],["pasitobulinusiais",1],["pasitobulinusiems",1],["pasitobulinčiau",1],["pasitobulinę",1],["pasitrainiojome",1],["pasitrainiojęs",1],["pasitrainioti",1],["pasitranauti",1],["pasitranko",1],["pasitrankysim",1],["pasitrankėme",1],["pasitraukdavom",1],["pasitraukdavome",1],["pasitraukdavusiu",1],["pasitraukdavęs",1],["pasitraukiantieji",1],["pasitraukiantiesiems",1],["pasitraukiantysis",1],["pasitrauksiantys",1],["pasitrauksiantį",1],["pasitrauksiančio",1],["pasitrauksiančios",1],["pasitrauksiančiu",1],["pasitrauksiančią",1],["pasitrauksiančių",1],["pasitrauksite",1],["pasitraukusiai",1],["pasitraukėt",1],["pasitraukņs",1],["pasitraulia",1],["pasitreiravus",1],["pasitreniruodavau",1],["pasitreniruoju",1],["pasitreniruok",1],["pasitreniruosime",1],["pasitreniruosiu",1],["pasitreniruotų",1],["pasitrigubins",1],["pasitrinant",1],["pasitrindavom",1],["pasitrinkime",1],["pasitrins",1],["pasitrintų",1],["pasitrnaudami",1],["pasitrokšti",1],["pasitroškinę",1],["pasitrumpintų",1],["pasitrumpinčiau",1],["pasitrumpinęs",1],["pasitrynusi",1],["pasitrynusių",1],["pasitrynęs",1],["pasitrypdavo",1],["pasitręšti",1],["pasitupdę",1],["pasitupdęs",1],["pasituriantis",1],["pasituriančiai",1],["pasituriančio",1],["pasituriančios",1],["pasiturimam",1],["pasiturimas",1],["pasiturimose",1],["pasiturimų",1],["pasiturinys",1],["pasiturinčiau",1],["pasiturinčiojo",1],["pasiturinčiuosius",1],["pasiturntis",1],["pasitursenant",1],["pasiturėjimas",1],["pasiturėjimą",1],["pasiturėjo",1],["pasiturėtojai",1],["pasituštinimo",1],["pasituštinti",1],["pasituštinusį",1],["pasitvarkant",1],["pasitvarkoma",1],["pasitvarkome",1],["pasitvarktyti",1],["pasitvarkykit",1],["pasitvarkymais",1],["pasitvarkymas",1],["pasitvarkymą",1],["pasitvarkysi",1],["pasitvarkysiu",1],["pasitvarkyt",1],["pasitvarkėme",1],["pasitvarkęs",1],["pasitvirtinant",1],["pasitvirtinanti",1],["pasitvirtinančios",1],["pasitvirtinančių",1],["pasitvirtindamos",1],["pasitvirtini",1],["pasitvirtinimą",1],["pasitvirtinom",1],["pasitvirtinsianti",1],["pasitvirtinsime",1],["pasitvirtintais",1],["pasitvirtintas",1],["pasitvirtints",1],["pasitvirtinusio",1],["pasitvirtinusią",1],["pasitvirtinusiųjų",1],["pasitvirtis",1],["pasitvėrus",1],["pasityrčiodamas",1],["pasityčiodavome",1],["pasityčiojai",1],["pasityčiojanti",1],["pasityčiojantys",1],["pasityčiojančios",1],["pasityčiojančiu",1],["pasityčioji",1],["pasityčiojime",1],["pasityčiojusieji",1],["pasityčiojusios",1],["pasityčiojusį",1],["pasityčiosiu",1],["pasityčiot",1],["pasitąso",1],["pasitąsome",1],["pasitąsymais",1],["pasitąsys",1],["pasitąsyti",1],["pasitąsė",1],["pasitūmėjo",1],["pasitūsinti",1],["pasiubagauti",1],["pasiucimas",1],["pasiukių",1],["pasiukvatysit",1],["pasiulė",1],["pasiun",1],["pasiuntas",1],["pasiuntate",1],["pasiuntimu",1],["pasiuntinei",1],["pasiuntines",1],["pasiuntininiais",1],["pasiuntiniuose",1],["pasiuntinukai",1],["pasiuntinuke",1],["pasiuntinukui",1],["pasiuntinuką",1],["pasiuntinybėmis",1],["pasiuntinybėn",1],["pasiuntinyste",1],["pasiuntinėja",1],["pasiuntu",1],["pasiuntusio",1],["pasiuntėt",1],["pasiunčiam",1],["pasiunčiamos",1],["pasiunčiamą",1],["pasiunčiamų",1],["pasiunčianti",1],["pasiunčiantis",1],["pasiunčiantys",1],["pasiunčiančių",1],["pasiunčiate",1],["pasiuogaudavom",1],["pasiuogaut",1],["pasiuogauti",1],["pasiuogavimas",1],["pasiurbiama",1],["pasiurbčiosi",1],["pasiurbė",1],["pasiusdavo",1],["pasiusi",1],["pasiusios",1],["pasiusioti",1],["pasiustų",1],["pasiustųjų",1],["pasiutbobei",1],["pasiutbobė",1],["pasiutbobę",1],["pasiutelio",1],["pasiutesnio",1],["pasiutesnių",1],["pasiuti",1],["pasiutimai",1],["pasiutiniai",1],["pasiutinybėje",1],["pasiutinį",1],["pasiutiška",1],["pasiutiškiausia",1],["pasiutllige",1],["pasiutninį",1],["pasiutpolke",1],["pasiutpolkei",1],["pasiutpolkes",1],["pasiutpolkių",1],["pasiuturtum",1],["pasiutusiame",1],["pasiutusias",1],["pasiutusiems",1],["pasiutusiomis",1],["pasiutusiuose",1],["pasiutvabalius",1],["pasiutybė",1],["pasiutėli",1],["pasiutėliams",1],["pasiutėlio",1],["pasiutėliu",1],["pasiutėliui",1],["pasiutėliškas",1],["pasiutėlės",1],["pasiutų",1],["pasiuvai",1],["pasiuvime",1],["pasiuvinėta",1],["pasiuvinėtas",1],["pasiuvinėtos",1],["pasiuvėjas",1],["pasiučiau",1],["pasiučiausius",1],["pasivadinant",1],["pasivadinantys",1],["pasivadindami",1],["pasivadines",1],["pasivadinimus",1],["pasivadinom",1],["pasivadinsi",1],["pasivadinsiantis",1],["pasivadinsiančia",1],["pasivadinta",1],["pasivadintum",1],["pasivadinu",1],["pasivadinusiais",1],["pasivadinusiame",1],["pasivadinusias",1],["pasivadinusis",1],["pasivadinčiau",1],["pasivadovauta",1],["pasivadovavau",1],["pasivagi",1],["pasivagiam",1],["pasivagiant",1],["pasivagiu",1],["pasivaidendavo",1],["pasivaidenimų",1],["pasivaidensiu",1],["pasivaidentų",1],["pasivaidenus",1],["pasivaidenusi",1],["pasivaidenąs",1],["pasivaidenę",1],["pasivaikyt",1],["pasivaikšiojimas",1],["pasivaikštinėjimo",1],["pasivaikštinėjimų",1],["pasivaikštom",1],["pasivaikščiodama",1],["pasivaikščiodamos",1],["pasivaikščiodavom",1],["pasivaikščiodavome",1],["pasivaikščiojai",1],["pasivaikščiojame",1],["pasivaikščiojantis",1],["pasivaikščiojančių",1],["pasivaikščiojau",1],["pasivaikščioji",1],["pasivaikščiojimi",1],["pasivaikščiojote",1],["pasivaikščiojusio",1],["pasivaikščiojusios",1],["pasivaikščiotum",1],["pasivaikščiotume",1],["pasivaikščiočiau",1],["pasivaikščojimai",1],["pasivaišinant",1],["pasivaišindamas",1],["pasivaišinimai",1],["pasivaišinimo",1],["pasivaišinimą",1],["pasivaišinkime",1],["pasivaišinu",1],["pasivaišinusiais",1],["pasivaišinusios",1],["pasivakarojimą",1],["pasivakščioti",1],["pasivalgymo",1],["pasivaliusios",1],["pasivalkioti",1],["pasivalo",1],["pasivalydavo",1],["pasivalykime",1],["pasivalyti",1],["pasivanojimu",1],["pasivanotų",1],["pasivargina",1],["pasivargino",1],["pasivarginta",1],["pasivarginti",1],["pasivartaliojome",1],["pasivartau",1],["pasivartydama",1],["pasivartydamas",1],["pasivartykime",1],["pasivartymas",1],["pasivartytų",1],["pasivartė",1]]}
